README
juggernaut.py
setup.py
juggernaut.egg-info/PKG-INFO
juggernaut.egg-info/SOURCES.txt
juggernaut.egg-info/dependency_links.txt
juggernaut.egg-info/not-zip-safe
juggernaut.egg-info/requires.txt
juggernaut.egg-info/top_level.txt