Metadata-Version: 1.0
Name: juggernaut
Version: 0.2
Summary: Client library for juggernaut.
Home-page: http://github.com/mitsuhiko/python-juggernaut
Author: Armin Ronacher
Author-email: armin.ronacher@active-4.com
License: UNKNOWN
Platform: UNKNOWN
Classifier: License :: OSI Approved :: BSD License
Classifier: Programming Language :: Python
